exalusAPI/__init__.py
exalusAPI/__main__.py
exalusAPI-0.6.2.dist-info/LICENSE
exalusAPI-0.6.2.dist-info/METADATA
exalusAPI-0.6.2.dist-info/WHEEL
exalusAPI-0.6.2.dist-info/top_level.txt
exalusAPI-0.6.2.dist-info/RECORD
