Metadata-Version: 2.1
Name: exalusAPI
Version: 0.6.2
Summary: Simple Exalus integration wrapper, created specifically for HomeAssistant integration.
Author-email: Marcel Janicki <majanicki00@gmail.com>
License: Apache License
Project-URL: Homepage, https://github.com/marceljanicki/exalusAPI
Keywords: HomeAssistant,Exalus
Classifier: License :: OSI Approved :: Apache Software License
Classifier: Programming Language :: Python
Classifier: Programming Language :: Python :: 3
Requires-Python: >=3.10.6
License-File: LICENSE
Requires-Dist: requests
Requires-Dist: signalrcore
